simbricks/runner/__init__.py
simbricks/runner/fragment_runner/__init__.py
simbricks/runner/fragment_runner/base.py
simbricks/runner/fragment_runner/local/__init__.py
simbricks/runner/fragment_runner/local/__main__.py
simbricks/runner/fragment_runner/local/settings.py
simbricks/runner/main_runner/__init__.py
simbricks/runner/main_runner/__main__.py
simbricks/runner/main_runner/plugins/__init__.py
simbricks/runner/main_runner/plugins/docker_plugin.py
simbricks/runner/main_runner/plugins/local_plugin.py
simbricks/runner/main_runner/plugins/plugin.py
simbricks/runner/main_runner/plugins/plugin_loader.py
simbricks/runner/main_runner/settings.py
simbricks/runner/utils.py
simbricks_runner-0.3.6.dist-info/METADATA
simbricks_runner-0.3.6.dist-info/WHEEL
simbricks_runner-0.3.6.dist-info/entry_points.txt
simbricks_runner-0.3.6.dist-info/RECORD
